rtl/core/rvseed_defines.v
// +FHDR------------------------------------------------------------------
//                 Copyright (c) 2022 
//                       ALL RIGHTS RESERVED
// -----------------------------------------------------------------------
// Filename      : rvseed_defines.v
// Author        : Rongye
// Created On    : 2022-03-21 20:17
// Last Modified : 2022-04-13 04:04
// -----------------------------------------------------------------------
// Description   : 
//
//
// -FHDR------------------------------------------------------------------

// simulation clock period
`define SIM_PERIOD 20 // 20ns -> 50MHz 

// processor numbers
`define CPU_WIDTH 32 // rv32

// instruction memory
`define INST_MEM_ADDR_DEPTH 1024
`define INST_MEM_ADDR_WIDTH 10 // 2^10 = 1024

// register 
`define REG_DATA_DEPTH 32
`define REG_ADDR_WIDTH 5 // 2^5 = 32

// immediate generate
`define INST_I_IMM_WIDTH 12
`define INST_S_IMM_WIDTH 12
`define INST_B_IMM_WIDTH 13
`define INST_U_IMM_WIDTH 32
`define INST_J_IMM_WIDTH 21

// instruction bits select
`define FUNCT3_BASE 12
`define FUNCT7_BASE 25
`define RD_BASE     7
`define RS1_BASE    15
`define RS2_BASE    20

// opcode
`define OPCODE_WIDTH 7
`define INST_TYPE_R  `OPCODE_WIDTH'b0110011 // add/sub/xor/or/and/sll/srl/sra/slt/sltu
`define INST_TYPE_I  `OPCODE_WIDTH'b0010011 // addi/xori/ori/andi/slli/srli/srai/slti/sltiu
`define INST_TYPE_IL `OPCODE_WIDTH'b0000011 // lb/lh/lw/lbu/lhu
`define INST_TYPE_S  `OPCODE_WIDTH'b0100011 // sb/sh/sw
`define INST_TYPE_B  `OPCODE_WIDTH'b1100011 // beq/bne/blt/bge/bltu/bgeu
`define INST_JAL     `OPCODE_WIDTH'b1101111 // jal
`define INST_JALR    `OPCODE_WIDTH'b1100111 // jalr
`define INST_LUI     `OPCODE_WIDTH'b0110111 // lui
`define INST_AUIPC   `OPCODE_WIDTH'b0010111 // auipc
`define INST_TYPE_IE `OPCODE_WIDTH'b1110011 // ecall/ebreak

// funct3
// R-type
`define FUNCT3_WIDTH 3
`define INST_ADD_SUB   `FUNCT3_WIDTH'h0 
`define INST_XOR       `FUNCT3_WIDTH'h4
`define INST_OR        `FUNCT3_WIDTH'h6
`define INST_AND       `FUNCT3_WIDTH'h7
`define INST_SLL       `FUNCT3_WIDTH'h1
`define INST_SRL_SRA   `FUNCT3_WIDTH'h5
`define INST_SLT       `FUNCT3_WIDTH'h2
`define INST_SLTU      `FUNCT3_WIDTH'h3
// I-type 
`define INST_ADDI      `FUNCT3_WIDTH'h0
`define INST_XORI      `FUNCT3_WIDTH'h4
`define INST_ORI       `FUNCT3_WIDTH'h6
`define INST_ANDI      `FUNCT3_WIDTH'h7
`define INST_SLLI      `FUNCT3_WIDTH'h1
`define INST_SRLI_SRAI `FUNCT3_WIDTH'h5 
`define INST_SLTI      `FUNCT3_WIDTH'h2
`define INST_SLTIU     `FUNCT3_WIDTH'h3
// I-type load
`define INST_LB        `FUNCT3_WIDTH'h0
`define INST_LH        `FUNCT3_WIDTH'h1
`define INST_LW        `FUNCT3_WIDTH'h2
`define INST_LBU       `FUNCT3_WIDTH'h4
`define INST_LHU       `FUNCT3_WIDTH'h5
// S-type
`define INST_SB        `FUNCT3_WIDTH'h0
`define INST_SH        `FUNCT3_WIDTH'h1
`define INST_SW        `FUNCT3_WIDTH'h2
// B-type
`define INST_BEQ       `FUNCT3_WIDTH'h0
`define INST_BNE       `FUNCT3_WIDTH'h1
`define INST_BLT       `FUNCT3_WIDTH'h4
`define INST_BGE       `FUNCT3_WIDTH'h5
`define INST_BLTU      `FUNCT3_WIDTH'h6
`define INST_BGEU      `FUNCT3_WIDTH'h7
// I-type environment
`define INST_ECALL     `FUNCT3_WIDTH'h0
`define INST_EBREAK    `FUNCT3_WIDTH'h0

// funct7
`define FUNCT7_WIDTH 7
`define FUNCT7_INST_A  `FUNCT7_WIDTH'h00
`define FUNCT7_INST_B  `FUNCT7_WIDTH'h20


// ALU opcode
`define ALU_OP_WIDTH 4
`define ALU_AND  `ALU_OP_WIDTH'b0000
`define ALU_OR   `ALU_OP_WIDTH'b0001
`define ALU_XOR  `ALU_OP_WIDTH'b0010
`define ALU_ADD  `ALU_OP_WIDTH'b0011
`define ALU_SUB  `ALU_OP_WIDTH'b0100
`define ALU_SLL  `ALU_OP_WIDTH'b0101 // shift left logical
`define ALU_SRL  `ALU_OP_WIDTH'b0110 // shift right logical
`define ALU_SRA  `ALU_OP_WIDTH'b0111 // shift right arith 
`define ALU_SLT  `ALU_OP_WIDTH'b1000 // set less than  
`define ALU_SLTU `ALU_OP_WIDTH'b1001 // set less than (unsigned) 
`define ALU_BLT  `ALU_OP_WIDTH'b1010 // branch less than
`define ALU_BLTU `ALU_OP_WIDTH'b1011 // branch less than (unsigned)
`define ALU_JAL  `ALU_OP_WIDTH'b1100  
`define ALU_JALR `ALU_OP_WIDTH'b1101  

// ALU select soure
`define ALU_SRC_WIDTH 2
`define ALU_SRC_REG     `ALU_SRC_WIDTH'b00 // src1 = reg1, src2 = reg2
`define ALU_SRC_IMM     `ALU_SRC_WIDTH'b01 // src1 = reg1, src2 = imm
`define ALU_SRC_FOUR_PC `ALU_SRC_WIDTH'b10 // src1 = 4,    src2 = pc
`define ALU_SRC_IMM_PC  `ALU_SRC_WIDTH'b11 // src1 = imm,  src2 = pc

// IMM GEN opcode
`define IMM_GEN_OP_WIDTH 3
`define IMM_GEN_I `IMM_GEN_OP_WIDTH'b000 
`define IMM_GEN_S `IMM_GEN_OP_WIDTH'b001
`define IMM_GEN_B `IMM_GEN_OP_WIDTH'b010
`define IMM_GEN_J `IMM_GEN_OP_WIDTH'b011
`define IMM_GEN_U `IMM_GEN_OP_WIDTH'b100

rtl/core/ctrl.v
// +FHDR----------------------------------------------------
//                   Copyright (c) 2023 
//                    ALL RIGHTS RESERVED
// ---------------------------------------------------------
// Filename         : ctrl.v
// Author           : zj
// Creater On       : 2023-03-24 17:11
// Last Modifying   : 
// ---------------------------------------------------------
// Description      : 
//
//
// -FHDR----------------------------------------------------
`include "rvseed_defines.v"

module ctrl(
    input               [`CPU_WIDTH-1:0]    inst,           // instruction input

    output reg                              branch,         // branch flag
    output reg                              jump,           // jump flag
    
    // 寄存器控制指令
    output reg                              reg_wen,        // register write enable    写使能
    output reg [`REG_ADDR_WIDTH-1:0]        reg_waddr,      // register write address   写地址
    output reg [`REG_ADDR_WIDTH-1:0]        reg1_raddr,     // register 1 read address  读地址1
    output reg [`REG_ADDR_WIDTH-1:0]        reg2_raddr,     // register 2 read address  读地址2
    
    //立即数扩展操作码
    output reg [`IMM_GEN_OP_WIDTH-1:0]      imm_gen_op,     // immediate extend opcode  立即数扩展的操作码

    output reg [`ALU_OP_WIDTH-1:0]          alu_op,         // alu opcode               alu的操作码
    output reg [`ALU_SRC_WIDTH-1:0]         alu_src_sel     // alu source select flag   alu的数据源选择
);

wire [`OPCODE_WIDTH-1:0]    opcode = inst[`OPCODE_WIDTH-1:0];
wire [`FUNCT3_WIDTH-1:0]    funct3 = inst[`FUNCT3_WIDTH + `FUNCT3_BASE-1:`FUNCT3_BASE];
wire [`FUNCT3_WIDTH-1:0]    funct7 = inst[`FUNCT7_WIDTH + `FUNCT7_BASE-1:`FUNCT7_BASE];
wire [`REG_ADDR_WIDTH-1:0]  rd     = inst[`REG_ADDR_WIDTH+`RD_BASE-1:`RD_BASE];
wire [`REG_ADDR_WIDTH-1:0]  rs1    = inst[`REG_ADDR_WIDTH+`RS1_BASE-1:`RS1_BASE];
wire [`REG_ADDR_WIDTH-1:0]  rs2    = inst[`REG_ADDR_WIDTH+`RS2_BASE-1:`RS2_BASE];

always @(*) begin
    branch                      = 1'b0;//这里在always初始就对各寄存器进行了初始化，后边的case即便没有default，仍然不会产生latch
    jump                        = 1'b0;
    reg_wen                     = 1'b0;
    // 此处的各初始值分别为：
    reg1_raddr                  = `REG_ADDR_WIDTH'b0; // 
    reg2_raddr                  = `REG_ADDR_WIDTH'b0;
    reg_waddr                   = `REG_ADDR_WIDTH'b0;
    imm_gen_op                  = `IMM_GEN_I;
    alu_op                      = `ALU_AND;
    alu_src_sel                 = `ALU_SRC_REG;
    
    case(opcode)
        `INST_TYPE_R:begin
            reg_wen         = 1'b1;
            reg1_addr       = rs1;
            reg2_addr       = rs2;
            reg_waddr       = rd;
            alu_src_sel     = `ALU_SRC_REG;
            case(funct3)
                `INST_ADD_SUB:
                    alu_op = (funct7 == `FUNCT7_INST_A) ? `ALU_ADD : `ALU_SUB;//add and sub
            endcase
        end
        `INST_TYPE_I:begin
            reg_wen         = 1'b1;
            reg1_addr       = rs1;
            reg_waddr       = rd;
            alu_src_sel     = `ALU_SRC_IMM;
            case(funct3)
                `INST_ADDI:begin
                    alu_op      = `ALU_ADD;
            endcase
        end
        `INST_TYPE_B:begin
            reg1_raddr      = rs1;
            reg2_raddr      = rs2;
            imm_gen_op      = `IMM_GEN_B;
            alu_src_sel     = `ALU_SRC_REG;
            case(funct3)
                `INST_BNE:begin
                    branch      = 1'b1; //分支跳转指令->分支跳转信号要拉高
                    alu_op      = `ALU_SUB;
                end
            endcase
        end
        `INST_JAL:begin
            jump            = 1'b1;
            reg_wen         = 1'b1;
            reg_waddr       = rd;
            imm_gen_op      = `IMM_GEN_J;
            alu_op          = `ALU_ADD;
            alu_src_sel     = `ALU_SRC_FOUR_PC;//PC+4
        end
        `INST_LUI:begin
            reg_wen         = 1'b1;
            reg1_raddr      = `REG_ADDR_WIDTH'b0;
            reg_waddr       = rd;
            imm_gen_op      = `IMM_GEN_U;
            alu_op          = `ALU_ADD;
            alu_src_sel     = `ALU_SRC_IMM;//x0 + imm
        end
    endcase
end

endmodule

rtl/core/defines.v
aaa
aaadadawdawdfawfaw

rtl/core/mux_pc.v
// +FHDR----------------------------------------------------
//                   Copyright (c) 2023 
//                    ALL RIGHTS RESERVED
// ---------------------------------------------------------
// Filename         : mux_pc.v
// Author           : zj
// Creater On       : 2023-03-24 11:12
// Last Modifying   : 
// ---------------------------------------------------------
// Description      : 
//
//
// -FHDR----------------------------------------------------
`include "defines.v"

module mux_pc(
    input                                   ena,
    input                                   branch,     // branch type
    input                                   zero,       // alu result is zero
    input                                   jump,       //jump type
    input   [`CPU_WIDTH-1:0]                imm,        // immediate
    input   [`CPU_WIDTH-1:0]                curr_pc,    // current pc addr
    output  [`CPU_WIDTH-1:0]                next_pc     // next pc addr
);

always @(*) begin
    if(~ena)
        next_pc = curr_pc;
    else if (branch && ~zero) // bne
        next_pc = curr_pc + imm;
    else if (jump)
        next_pc = curr_pc + imm;
    else
        next_pc = curr_pc + `CPU_WIDTH'h4;
end

endmodule

rtl/core/inst_mem.v
// +FHDR----------------------------------------------------
//                   Copyright (c) 2023 
//                    ALL RIGHTS RESERVED
// ---------------------------------------------------------
// Filename         : inst_mem.v
// Author           : zj
// Creater On       : 2023-03-23 22:48
// Last Modifying   : 
// ---------------------------------------------------------
// Description      :
//      输入：需要的指令的地址
//      输出：当前地址处的指令inst
// -FHDR----------------------------------------------------


`include "defines.v"
module inst_mem(
    input       [`CPU_WIDTH-1:0] curr_pc,   // current pc addr
    output      [`CPU_WIDTH-1:0] inst       // instruction  riscv的指令是32位的
);

reg [`CPU_WIDTH-1:0] inst_mem_f [`INST_MEM_ADDR_DEPTH-1:0];// 统一高位在左，低位在右,前边是宽度，后边是深度

always @(*) begin
    inst = inst_mem_f[curr_pc[`INST_MEM_ADDR_WIDTH+2-1:2]];
end
endmodule

rtl/tb/tb_rvseed.v
// +FHDR----------------------------------------------------------------------------
//                 Copyright (c) 2022 
//                       ALL RIGHTS RESERVED
// ---------------------------------------------------------------------------------
// Filename      : tb_rvseed.v
// Author        : Rongye
// Created On    : 2022-03-25 04:18
// Last Modified : 2022-04-13 19:41
// ---------------------------------------------------------------------------------
// Description   : 
//
//
// -FHDR----------------------------------------------------------------------------
`timescale 1ns / 1ps
`include "rvseed_defines.v"

module tb_rvseed ();

reg                  clk;
reg                  rst_n;
reg                  zero;
reg [`CPU_WIDTH-1:0] imm;
reg [5*8-1:0]        inst_name;
wire                 branch;     // branch flag
wire                 jump;       // jump flag

wire                  ena;
wire [`CPU_WIDTH-1:0] next_pc; 
wire [`CPU_WIDTH-1:0] curr_pc; 
wire [`CPU_WIDTH-1:0] inst; 

wire                         reg_wen;    // register write enable
wire [`REG_ADDR_WIDTH-1:0]   reg_waddr;  // register write address
wire [`REG_ADDR_WIDTH-1:0]   reg1_raddr; // register 1 read address
wire [`REG_ADDR_WIDTH-1:0]   reg2_raddr; // register 2 read address

wire [`IMM_GEN_OP_WIDTH-1:0] imm_gen_op; // immediate extend opcode

wire [`ALU_OP_WIDTH-1:0]     alu_op;     // alu opcode
wire [`ALU_SRC_WIDTH-1:0]    alu_src_sel;// alu source select flag


initial begin
    #(`SIM_PERIOD/2);
    clk       = 1'b0;
    rst_n     = 1'b0;
    
    zero      = 1'b1;
    imm       = `CPU_WIDTH'h8;
    inst_name = "ADD";
    inst_load(inst_name);
    
    #(`SIM_PERIOD * 1);
    rst_n = 1'b1;
    #(`SIM_PERIOD * 500);
    $stop;
end

initial begin
    #(`SIM_PERIOD * 50000);
    $display("Time Out");
    $finish;
end

always #(`SIM_PERIOD/2) clk = ~clk;

task reset;                // reset 1 clock
    begin
        rst_n = 0; 
        #(`SIM_PERIOD * 1);
        rst_n = 1;
    end
endtask

task inst_load;
    input [5*8-1:0] inst_name;
    begin
        $readmemh (inst_name, u_inst_mem_0. inst_mem_f);
    end
endtask


pc_reg u_pc_reg_0(
    .clk                            ( clk                           ),
    .rst_n                          ( rst_n                         ),
    .ena                            ( ena                           ),
    .next_pc                        ( next_pc                       ),
    .curr_pc                        ( curr_pc                       )
);

inst_mem u_inst_mem_0(
    .curr_pc                        ( curr_pc                       ),
    .inst                           ( inst                          )
);

mux_pc u_mux_pc_0(
    .ena                            ( ena                           ),
    .branch                         ( branch                        ),
    .zero                           ( zero                          ),
    .jump                           ( jump                          ),
    .imm                            ( imm                           ),
    .curr_pc                        ( curr_pc                       ),
    .next_pc                        ( next_pc                       )
);

ctrl u_ctrl_0(
    .inst                           ( inst                          ),
    .branch                         ( branch                        ),
    .jump                           ( jump                          ),
    .reg_wen                        ( reg_wen                       ),
    .reg_waddr                      ( reg_waddr                     ),
    .reg1_raddr                     ( reg1_raddr                    ),
    .reg2_raddr                     ( reg2_raddr                    ),
    .imm_gen_op                     ( imm_gen_op                    ),
    .alu_op                         ( alu_op                        ),
    .alu_src_sel                    ( alu_src_sel                   )
);


// iverilog 
initial begin
    $dumpfile("sim_out.vcd");
    $dumpvars;
end

endmodule

rtl/tb/sim_out.vcd
$date
	Wed Apr 13 19:44:07 2022
$end
$version
	Icarus Verilog
$end
$timescale
	1ps
$end
$scope module tb_rvseed $end
$var wire 1 ! reg_wen $end
$var wire 5 " reg_waddr [4:0] $end
$var wire 5 # reg2_raddr [4:0] $end
$var wire 5 $ reg1_raddr [4:0] $end
$var wire 32 % next_pc [31:0] $end
$var wire 1 & jump $end
$var wire 32 ' inst [31:0] $end
$var wire 3 ( imm_gen_op [2:0] $end
$var wire 1 ) ena $end
$var wire 32 * curr_pc [31:0] $end
$var wire 1 + branch $end
$var wire 2 , alu_src_sel [1:0] $end
$var wire 4 - alu_op [3:0] $end
$var reg 1 . clk $end
$var reg 32 / imm [31:0] $end
$var reg 40 0 inst_name [39:0] $end
$var reg 1 1 rst_n $end
$var reg 1 2 zero $end
$scope module u_ctrl_0 $end
$var wire 5 3 rs2 [4:0] $end
$var wire 5 4 rs1 [4:0] $end
$var wire 5 5 rd [4:0] $end
$var wire 7 6 opcode [6:0] $end
$var wire 32 7 inst [31:0] $end
$var wire 7 8 funct7 [6:0] $end
$var wire 3 9 funct3 [2:0] $end
$var reg 4 : alu_op [3:0] $end
$var reg 2 ; alu_src_sel [1:0] $end
$var reg 1 + branch $end
$var reg 3 < imm_gen_op [2:0] $end
$var reg 1 & jump $end
$var reg 5 = reg1_raddr [4:0] $end
$var reg 5 > reg2_raddr [4:0] $end
$var reg 5 ? reg_waddr [4:0] $end
$var reg 1 ! reg_wen $end
$upscope $end
$scope module u_inst_mem_0 $end
$var wire 32 @ curr_pc [31:0] $end
$var reg 32 A inst [31:0] $end
$upscope $end
$scope module u_mux_pc_0 $end
$var wire 1 + branch $end
$var wire 32 B imm [31:0] $end
$var wire 1 & jump $end
$var wire 1 2 zero $end
$var wire 1 ) ena $end
$var wire 32 C curr_pc [31:0] $end
$var reg 32 D next_pc [31:0] $end
$upscope $end
$scope module u_pc_reg_0 $end
$var wire 1 . clk $end
$var wire 32 E next_pc [31:0] $end
$var wire 1 1 rst_n $end
$var reg 32 F curr_pc [31:0] $end
$var reg 1 ) ena $end
$upscope $end
$scope task inst_load $end
$var reg 40 G inst_name [39:0] $end
$upscope $end
$scope task reset $end
$upscope $end
$upscope $end
$enddefinitions $end
#0
$dumpvars
bx G
bx F
bx E
bx D
bx C
bx B
bx A
bx @
bx ?
bx >
bx =
bx <
bx ;
bx :
bx 9
bx 8
bx 7
bx 6
bx 5
bx 4
bx 3
x2
x1
bx 0
bx /
x.
bx -
bx ,
x+
bx *
x)
bx (
bx '
x&
bx %
bx $
bx #
bx "
x!
$end
#10000
b1 ,
b1 ;
b11 -
b11 :
b0 (
b0 <
b11010 "
b11010 ?
b0 #
b0 >
b0 $
b0 =
1!
0&
0+
b0 3
b0 4
b11010 5
b0 8
b0 9
b10011 6
b110100010011 '
b110100010011 7
b110100010011 A
b0 %
b0 D
b0 E
0)
b0 *
b0 @
b0 C
b0 F
b10000010100010001000100 G
b10000010100010001000100 0
b1000 /
b1000 B
12
01
1.
#20000
0.
#30000
b100 %
b100 D
b100 E
1)
1.
11
#40000
0.
#50000
b1 ,
b1 ;
b11 -
b11 :
b11011 "
b11011 ?
1!
b11011 5
b110110010011 '
b110110010011 7
b110110010011 A
b1000 %
b1000 D
b1000 E
b100 *
b100 @
b100 C
b100 F
1.
#60000
0.
#70000
b1 ,
b1 ;
b11 -
b11 :
b1 "
b1 ?
1!
b1 5
b10010011 '
b10010011 7
b10010011 A
b1100 %
b1100 D
b1100 E
b1000 *
b1000 @
b1000 C
b1000 F
1.
#80000
0.
#90000
b1 ,
b1 ;
b11 -
b11 :
b10 "
b10 ?
1!
b10 5
b100010011 '
b100010011 7
b100010011 A
b10000 %
b10000 D
b10000 E
b1100 *
b1100 @
b1100 C
b1100 F
1.
#100000
0.
#110000
b10 #
b10 >
b1 $
b1 =
b0 ,
b0 ;
b11 -
b11 :
b11110 "
b11110 ?
1!
b10 3
b1 4
b11110 5
b110011 6
b1000001000111100110011 '
b1000001000111100110011 7
b1000001000111100110011 A
b10100 %
b10100 D
b10100 E
b10000 *
b10000 @
b10000 C
b10000 F
1.
#120000
0.
#130000
b1 ,
b1 ;
b11 -
b11 :
b11101 "
b11101 ?
b0 #
b0 >
b0 $
b0 =
1!
b0 3
b0 4
b11101 5
b10011 6
b111010010011 '
b111010010011 7
b111010010011 A
b11000 %
b11000 D
b11000 E
b10100 *
b10100 @
b10100 C
b10100 F
1.
#140000
0.
#150000
b1 ,
b1 ;
b11 -
b11 :
b11 "
b11 ?
1!
b10 3
b11 5
b1000000000000110010011 '
b1000000000000110010011 7
b1000000000000110010011 A
b11100 %
b11100 D
b11100 E
b11000 *
b11000 @
b11000 C
b11000 F
1.
#160000
0.
#170000
1+
b10 (
b10 <
b11101 #
b11101 >
b11110 $
b11110 =
b0 ,
b0 ;
b100 -
b100 :
b0 "
b0 ?
0!
b11101 3
b11110 4
b1100 5
b100110 8
b1 9
b1100011 6
b1001101110111110001011001100011 '
b1001101110111110001011001100011 7
b1001101110111110001011001100011 A
b100000 %
b100000 D
b100000 E
b11100 *
b11100 @
b11100 C
b11100 F
1.
#180000
0.
#190000
b1 ,
b1 ;
b1 "
b1 ?
1!
b11 -
b11 :
b0 (
b0 <
b0 #
b0 >
b0 $
b0 =
0+
b1 3
b0 4
b1 5
b0 8
b0 9
b10011 6
b100000000000010010011 '
b100000000000010010011 7
b100000000000010010011 A
b100100 %
b100100 D
b100100 E
b100000 *
b100000 @
b100000 C
b100000 F
1.
#200000
0.
#210000
b1 ,
b1 ;
b11 -
b11 :
b10 "
b10 ?
1!
b10 5
b100000000000100010011 '
b100000000000100010011 7
b100000000000100010011 A
b101000 %
b101000 D
b101000 E
b100100 *
b100100 @
b100100 C
b100100 F
1.
#220000
0.
#230000
b10 #
b10 >
b1 $
b1 =
b0 ,
b0 ;
b11 -
b11 :
b11110 "
b11110 ?
1!
b10 3
b1 4
b11110 5
b110011 6
b1000001000111100110011 '
b1000001000111100110011 7
b1000001000111100110011 A
b101100 %
b101100 D
b101100 E
b101000 *
b101000 @
b101000 C
b101000 F
1.
#240000
0.
#250000
b1 ,
b1 ;
b11 -
b11 :
b11101 "
b11101 ?
b0 #
b0 >
b0 $
b0 =
1!
b0 4
b11101 5
b10011 6
b1000000000111010010011 '
b1000000000111010010011 7
b1000000000111010010011 A
b110000 %
b110000 D
b110000 E
b101100 *
b101100 @
b101100 C
b101100 F
1.
#260000
0.
#270000
b1 ,
b1 ;
b11 -
b11 :
b11 "
b11 ?
1!
b11 3
b11 5
b1100000000000110010011 '
b1100000000000110010011 7
b1100000000000110010011 A
b110100 %
b110100 D
b110100 E
b110000 *
b110000 @
b110000 C
b110000 F
1.
#280000
0.
#290000
1+
b10 (
b10 <
b11101 #
b11101 >
b11110 $
b11110 =
b0 ,
b0 ;
b100 -
b100 :
b0 "
b0 ?
0!
b11101 3
b11110 4
b10100 5
b100101 8
b1 9
b1100011 6
b1001011110111110001101001100011 '
b1001011110111110001101001100011 7
b1001011110111110001101001100011 A
b111000 %
b111000 D
b111000 E
b110100 *
b110100 @
b110100 C
b110100 F
1.
#300000
0.
#310000
b1 ,
b1 ;
b1 "
b1 ?
1!
b11 -
b11 :
b0 (
b0 <
b0 #
b0 >
b0 $
b0 =
0+
b11 3
b0 4
b1 5
b0 8
b0 9
b10011 6
b1100000000000010010011 '
b1100000000000010010011 7
b1100000000000010010011 A
b111100 %
b111100 D
b111100 E
b111000 *
b111000 @
b111000 C
b111000 F
1.
#320000
0.
#330000
b1 ,
b1 ;
b11 -
b11 :
b10 "
b10 ?
1!
b111 3
b10 5
b11100000000000100010011 '
b11100000000000100010011 7
b11100000000000100010011 A
b1000000 %
b1000000 D
b1000000 E
b111100 *
b111100 @
b111100 C
b111100 F
1.
#340000
0.
#350000
b10 #
b10 >
b1 $
b1 =
b0 ,
b0 ;
b11 -
b11 :
b11110 "
b11110 ?
1!
b10 3
b1 4
b11110 5
b110011 6
b1000001000111100110011 '
b1000001000111100110011 7
b1000001000111100110011 A
b1000100 %
b1000100 D
b1000100 E
b1000000 *
b1000000 @
b1000000 C
b1000000 F
1.
#360000
0.
#370000
b1 ,
b1 ;
b11 -
b11 :
b11101 "
b11101 ?
b0 #
b0 >
b0 $
b0 =
1!
b1010 3
b0 4
b11101 5
b10011 6
b101000000000111010010011 '
b101000000000111010010011 7
b101000000000111010010011 A
b1001000 %
b1001000 D
b1001000 E
b1000100 *
b1000100 @
b1000100 C
b1000100 F
1.
#380000
0.
#390000
b1 ,
b1 ;
b11 -
b11 :
b11 "
b11 ?
1!
b100 3
b11 5
b10000000000000110010011 '
b10000000000000110010011 7
b10000000000000110010011 A
b1001100 %
b1001100 D
b1001100 E
b1001000 *
b1001000 @
b1001000 C
b1001000 F
1.
#400000
0.
#410000
1+
b10 (
b10 <
b11101 #
b11101 >
b11110 $
b11110 =
b0 ,
b0 ;
b100 -
b100 :
b0 "
b0 ?
0!
b11101 3
b11110 4
b11100 5
b100100 8
b1 9
b1100011 6
b1001001110111110001111001100011 '
b1001001110111110001111001100011 7
b1001001110111110001111001100011 A
b1010000 %
b1010000 D
b1010000 E
b1001100 *
b1001100 @
b1001100 C
b1001100 F
1.
#420000
0.
#430000
b1 ,
b1 ;
b1 "
b1 ?
1!
b11 -
b11 :
b0 (
b0 <
b0 #
b0 >
b0 $
b0 =
0+
b0 3
b0 4
b1 5
b0 8
b0 9
b10011 6
b10010011 '
b10010011 7
b10010011 A
b1010100 %
b1010100 D
b1010100 E
b1010000 *
b1010000 @
b1010000 C
b1010000 F
1.
#440000
0.
#450000
b100 (
b100 <
b1 ,
b1 ;
b11 -
b11 :
b10 "
b10 ?
1!
b11111 3
b11111 4
b10 5
b1111111 8
b110111 6
b11111111111111111000000100110111 '
b11111111111111111000000100110111 7
b11111111111111111000000100110111 A
b1011000 %
b1011000 D
b1011000 E
b1010100 *
b1010100 @
b1010100 C
b1010100 F
1.
#460000
0.
#470000
b10 #
b10 >
b1 $
b1 =
b0 ,
b0 ;
b11 -
b11 :
b0 (
b0 <
b11110 "
b11110 ?
1!
b10 3
b1 4
b11110 5
b0 8
b110011 6
b1000001000111100110011 '
b1000001000111100110011 7
b1000001000111100110011 A
b1011100 %
b1011100 D
b1011100 E
b1011000 *
b1011000 @
b1011000 C
b1011000 F
1.
#480000
0.
#490000
b1 ,
b1 ;
b100 (
b100 <
b11 -
b11 :
b11101 "
b11101 ?
b0 #
b0 >
b0 $
b0 =
1!
b11111 3
b11111 4
b11101 5
b1111111 8
b110111 6
b11111111111111111000111010110111 '
b11111111111111111000111010110111 7
b11111111111111111000111010110111 A
b1100000 %
b1100000 D
b1100000 E
b1011100 *
b1011100 @
b1011100 C
b1011100 F
1.
#500000
0.
#510000
b1 ,
b1 ;
b11 -
b11 :
b0 (
b0 <
b11 "
b11 ?
1!
b101 3
b0 4
b11 5
b0 8
b10011 6
b10100000000000110010011 '
b10100000000000110010011 7
b10100000000000110010011 A
b1100100 %
b1100100 D
b1100100 E
b1100000 *
b1100000 @
b1100000 C
b1100000 F
1.
#520000
0.
#530000
1+
b10 (
b10 <
b11101 #
b11101 >
b11110 $
b11110 =
b0 ,
b0 ;
b100 -
b100 :
b0 "
b0 ?
0!
b11101 3
b11110 4
b100 5
b100100 8
b1 9
b1100011 6
b1001001110111110001001001100011 '
b1001001110111110001001001100011 7
b1001001110111110001001001100011 A
b1101000 %
b1101000 D
b1101000 E
b1100100 *
b1100100 @
b1100100 C
b1100100 F
1.
#540000
0.
#550000
b1 ,
b1 ;
b1 "
b1 ?
1!
b11 -
b11 :
b100 (
b100 <
b0 #
b0 >
b0 $
b0 =
0+
b0 3
b0 4
b1 5
b1000000 8
b0 9
b110111 6
b10000000000000000000000010110111 '
b10000000000000000000000010110111 7
b10000000000000000000000010110111 A
b1101100 %
b1101100 D
b1101100 E
b1101000 *
b1101000 @
b1101000 C
b1101000 F
1.
#560000
0.
#570000
b1 ,
b1 ;
b11 -
b11 :
b0 (
b0 <
b10 "
b10 ?
1!
b10 5
b0 8
b10011 6
b100010011 '
b100010011 7
b100010011 A
b1110000 %
b1110000 D
b1110000 E
b1101100 *
b1101100 @
b1101100 C
b1101100 F
1.
#580000
0.
#590000
b10 #
b10 >
b1 $
b1 =
b0 ,
b0 ;
b11 -
b11 :
b11110 "
b11110 ?
1!
b10 3
b1 4
b11110 5
b110011 6
b1000001000111100110011 '
b1000001000111100110011 7
b1000001000111100110011 A
b1110100 %
b1110100 D
b1110100 E
b1110000 *
b1110000 @
b1110000 C
b1110000 F
1.
#600000
0.
#610000
b1 ,
b1 ;
b100 (
b100 <
b11 -
b11 :
b11101 "
b11101 ?
b0 #
b0 >
b0 $
b0 =
1!
b0 3
b0 4
b11101 5
b1000000 8
b110111 6
b10000000000000000000111010110111 '
b10000000000000000000111010110111 7
b10000000000000000000111010110111 A
b1111000 %
b1111000 D
b1111000 E
b1110100 *
b1110100 @
b1110100 C
b1110100 F
1.
#620000
0.
#630000
b1 ,
b1 ;
b11 -
b11 :
b0 (
b0 <
b11 "
b11 ?
1!
b110 3
b11 5
b0 8
b10011 6
b11000000000000110010011 '
b11000000000000110010011 7
b11000000000000110010011 A
b1111100 %
b1111100 D
b1111100 E
b1111000 *
b1111000 @
b1111000 C
b1111000 F
1.
#640000
0.
#650000
1+
b10 (
b10 <
b11101 #
b11101 >
b11110 $
b11110 =
b0 ,
b0 ;
b100 -
b100 :
b0 "
b0 ?
0!
b11101 3
b11110 4
b1100 5
b100011 8
b1 9
b1100011 6
b1000111110111110001011001100011 '
b1000111110111110001011001100011 7
b1000111110111110001011001100011 A
b10000000 %
b10000000 D
b10000000 E
b1111100 *
b1111100 @
b1111100 C
b1111100 F
1.
#660000
0.
#670000
b1 ,
b1 ;
b1 "
b1 ?
1!
b11 -
b11 :
b100 (
b100 <
b0 #
b0 >
b0 $
b0 =
0+
b0 3
b0 4
b1 5
b1000000 8
b0 9
b110111 6
b10000000000000000000000010110111 '
b10000000000000000000000010110111 7
b10000000000000000000000010110111 A
b10000100 %
b10000100 D
b10000100 E
b10000000 *
b10000000 @
b10000000 C
b10000000 F
1.
#680000
0.
#690000
b1 ,
b1 ;
b11 -
b11 :
b100 (
b100 <
b10 "
b10 ?
1!
b11111 3
b11111 4
b10 5
b1111111 8
b11111111111111111000000100110111 '
b11111111111111111000000100110111 7
b11111111111111111000000100110111 A
b10001000 %
b10001000 D
b10001000 E
b10000100 *
b10000100 @
b10000100 C
b10000100 F
1.
#700000
0.
#710000
b10 #
b10 >
b1 $
b1 =
b0 ,
b0 ;
b11 -
b11 :
b0 (
b0 <
b11110 "
b11110 ?
1!
b10 3
b1 4
b11110 5
b0 8
b110011 6
b1000001000111100110011 '
b1000001000111100110011 7
b1000001000111100110011 A
b10001100 %
b10001100 D
b10001100 E
b10001000 *
b10001000 @
b10001000 C
b10001000 F
1.
#720000
0.
